[
  {
    "path": "/yi-Xu-0100/hugo-theme-whiteink",
    "title": "yi-Xu-0100/hugo-theme-whiteink: hugo-theme-whiteink for yixuju",
    "count": 2,
    "uniques": 2
  },
  {
    "path": "/yi-Xu-0100/hugo-theme-whiteink/blob/main/layouts/_default/single.html",
    "title": "hugo-theme-whiteink/single.html at main · yi-Xu-0100/hugo-theme-whiteink · Gi...",
    "count": 2,
    "uniques": 1
  },
  {
    "path": "/yi-Xu-0100/hugo-theme-whiteink/blob/main/layouts/partials/head.html",
    "title": "hugo-theme-whiteink/head.html at main · yi-Xu-0100/hugo-theme-whiteink · GitHub",
    "count": 2,
    "uniques": 1
  },
  {
    "path": "/yi-Xu-0100/hugo-theme-whiteink/tree/main/layouts/_default",
    "title": "hugo-theme-whiteink/layouts/_default at main · yi-Xu-0100/hugo-theme-whiteink...",
    "count": 2,
    "uniques": 1
  },
  {
    "path": "/yi-Xu-0100/hugo-theme-whiteink/tree/main/layouts/partials",
    "title": "hugo-theme-whiteink/layouts/partials at main · yi-Xu-0100/hugo-theme-whiteink...",
    "count": 2,
    "uniques": 1
  },
  {
    "path": "/yi-Xu-0100/hugo-theme-whiteink/blob/main/layouts/_default/baseof.html",
    "title": "hugo-theme-whiteink/baseof.html at main · yi-Xu-0100/hugo-theme-whiteink · Gi...",
    "count": 1,
    "uniques": 1
  },
  {
    "path": "/yi-Xu-0100/hugo-theme-whiteink/blob/main/layouts/partials/footer.html",
    "title": "hugo-theme-whiteink/footer.html at main · yi-Xu-0100/hugo-theme-whiteink · Gi...",
    "count": 1,
    "uniques": 1
  },
  {
    "path": "/yi-Xu-0100/hugo-theme-whiteink/blob/main/layouts/partials/header.html",
    "title": "hugo-theme-whiteink/header.html at main · yi-Xu-0100/hugo-theme-whiteink · Gi...",
    "count": 1,
    "uniques": 1
  },
  {
    "path": "/yi-Xu-0100/hugo-theme-whiteink/blob/main/layouts/partials/main.html",
    "title": "hugo-theme-whiteink/main.html at main · yi-Xu-0100/hugo-theme-whiteink · GitHub",
    "count": 1,
    "uniques": 1
  },
  {
    "path": "/yi-Xu-0100/hugo-theme-whiteink/tree/main/layouts",
    "title": "hugo-theme-whiteink/layouts at main · yi-Xu-0100/hugo-theme-whiteink · GitHub",
    "count": 1,
    "uniques": 1
  }
]