{
  "count": 37,
  "uniques": 30,
  "clones": [
    {
      "timestamp": "2021-04-29T00:00:00Z",
      "count": 5,
      "uniques": 4
    },
    {
      "timestamp": "2021-04-30T00:00:00Z",
      "count": 3,
      "uniques": 2
    },
    {
      "timestamp": "2021-05-01T00:00:00Z",
      "count": 5,
      "uniques": 4
    },
    {
      "timestamp": "2021-05-02T00:00:00Z",
      "count": 6,
      "uniques": 5
    },
    {
      "timestamp": "2021-05-03T00:00:00Z",
      "count": 6,
      "uniques": 5
    },
    {
      "timestamp": "2021-05-04T00:00:00Z",
      "count": 7,
      "uniques": 6
    },
    {
      "timestamp": "2021-05-05T00:00:00Z",
      "count": 5,
      "uniques": 4
    }
  ]
}