[
  {
    "path": "/yi-Xu-0100/traffic2badge/issues",
    "title": "Issues · yi-Xu-0100/traffic2badge · GitHub",
    "count": 2,
    "uniques": 2
  },
  {
    "path": "/yi-Xu-0100/traffic2badge/tree/traffic",
    "title": "GitHub - yi-Xu-0100/traffic2badge at traffic",
    "count": 2,
    "uniques": 2
  },
  {
    "path": "/yi-Xu-0100/traffic2badge",
    "title": "GitHub - yi-Xu-0100/traffic2badge: Traffic to badge action usage template. Us...",
    "count": 1,
    "uniques": 1
  },
  {
    "path": "/yi-Xu-0100/traffic2badge/blob/traffic/traffic-purewriter-FAQ/clones.svg",
    "title": "traffic2badge/clones.svg at traffic · yi-Xu-0100/traffic2badge · GitHub",
    "count": 1,
    "uniques": 1
  },
  {
    "path": "/yi-Xu-0100/traffic2badge/issues/8",
    "title": "The TOC of readme can be deleted · Issue #8 · yi-Xu-0100/traffic2badge · GitHub",
    "count": 1,
    "uniques": 1
  },
  {
    "path": "/yi-Xu-0100/traffic2badge/tree/traffic/traffic-purewriter-FAQ",
    "title": "traffic2badge/traffic-purewriter-FAQ at traffic · yi-Xu-0100/traffic2badge · ...",
    "count": 1,
    "uniques": 1
  }
]