[
  {
    "path": "/yi-Xu-0100/Application-Lists",
    "title": "yi-Xu-0100/Application-Lists: 个人使用的应用程序列表，备用和备忘。",
    "count": 9,
    "uniques": 7
  },
  {
    "path": "/yi-Xu-0100/Application-Lists/pull/100",
    "title": "chore(deps): ⬆️ bump prismjs from 1.26.0 to 1.27.0 by dependabot[bot] · Pull ...",
    "count": 1,
    "uniques": 1
  },
  {
    "path": "/yi-Xu-0100/Application-Lists/pull/98",
    "title": "chore(deps): ⬆️ bump actions/github-script from 5 to 6 by dependabot[bot] · P...",
    "count": 1,
    "uniques": 1
  },
  {
    "path": "/yi-Xu-0100/Application-Lists/pull/99",
    "title": "chore(deps): ⬆️ bump lint-staged from 12.3.3 to 12.3.4 by dependabot[bot] · P...",
    "count": 1,
    "uniques": 1
  }
]